{
  "model_name": "GibsonLanni",
  "id": "DefaultGibsonLanniConfig",
  "res_lateral_nm": 2500,
  "res_axial_nm": 2500,
  "size_x": 256,
  "size_y": 256,
  "size_z": 256,
  "NA": 1.4,
  "lambda_nm": 450.0,
  "accuracy": 32,
  "working_distance_design_nm": 150000.0,
  "working_distance_experimental_nm": 150000.0,
  "immersion_ri_design": 1.515,
  "immersion_ri_experimental": 1.515,
  "coverslip_thickness_design_nm": 170.0,
  "coverslip_thickness_experimental_nm": 170.0,
  "coverslip_ri_design": 1.5,
  "coverslip_ri_experimental": 1.5,
  "sample_ri": 1.33,
  "particle_axial_position_nm": 0.0,
  "pixel_size_axial_nm": 100.0,
  "pixel_size_lateral_nm": 100.0
}
